dictionary_simplifier/__init__.py
dictionary_simplifier/simplifier.py
dictionary_simplifier-0.1.0.dist-info/WHEEL
dictionary_simplifier-0.1.0.dist-info/METADATA
dictionary_simplifier-0.1.0.dist-info/RECORD
