Metadata-Version: 2.1
Name: dictionary-simplifier
Version: 0.1.0
Summary: Simplify python dictionary operations with custom function
Author: Md. Sany Ahmed
Author-email: sany2k8@gmail.com
Requires-Python: >=3.10.9,<4.0.0
Classifier: Programming Language :: Python :: 3
Classifier: Programming Language :: Python :: 3.11
Requires-Dist: bandit (>=1.7.4,<2.0.0)
Requires-Dist: black (>=23.1.0,<24.0.0)
Requires-Dist: flake8 (>=6.0.0,<7.0.0)
Requires-Dist: isort (>=5.12.0,<6.0.0)
Requires-Dist: pytest (>=7.2.2,<8.0.0)
